landingai/__init__.py
landingai/common.py
landingai/data_management/__init__.py
landingai/data_management/client.py
landingai/data_management/dataset.py
landingai/data_management/label.py
landingai/data_management/media.py
landingai/data_management/metadata.py
landingai/data_management/utils.py
landingai/exceptions.py
landingai/fonts/default_font_ch_en.ttf
landingai/image_source_ops.py
landingai/notebook_utils.py
landingai/pipeline/__init__.py
landingai/pipeline/frameset.py
landingai/pipeline/image_source.py
landingai/pipeline/postprocessing.py
landingai/postprocess.py
landingai/predict/__init__.py
landingai/predict/cloud.py
landingai/predict/edge.py
landingai/predict/ocr.py
landingai/predict/snowflake.py
landingai/predict/utils.py
landingai/st_utils.py
landingai/storage/__init__.py
landingai/storage/data_access.py
landingai/storage/snowflake.py
landingai/telemetry.py
landingai/timer.py
landingai/transform.py
landingai/utils.py
landingai/visualize.py
landingai-0.3.49.dist-info/LICENSE.md
landingai-0.3.49.dist-info/METADATA
landingai-0.3.49.dist-info/WHEEL
landingai-0.3.49.dist-info/RECORD
