Metadata-Version: 2.1
Name: landingai
Version: 0.3.49
Summary: Helper library for interacting with LandingAI LandingLens
Author: LandingAI
Author-email: dev@landing.ai
Requires-Python: >=3.9,<4.0
Classifier: Programming Language :: Python :: 3
Classifier: Programming Language :: Python :: 3.9
Classifier: Programming Language :: Python :: 3.10
Classifier: Programming Language :: Python :: 3.11
Provides-Extra: snowflake
Requires-Dist: aiofiles (>=0.7.0,<1.0.0)
Requires-Dist: aiohttp[speedups] (>=3.7.3,<4.0.0)
Requires-Dist: bbox-visualizer (>=0.1.0,<0.2.0)
Requires-Dist: cryptography (>=39.0.0,<40.0.0) ; extra == "snowflake"
Requires-Dist: imageio[ffmpeg] (>=2.0.0,<3.0.0)
Requires-Dist: numpy (>=1.21.0,<2.0.0)
Requires-Dist: opencv-python (>=4.5,<5.0)
Requires-Dist: pandas (>=2.0.0,<3.0.0)
Requires-Dist: pillow (>=9.0,<11.0)
Requires-Dist: pydantic (>=2.0.0,<3.0.0)
Requires-Dist: pydantic-settings (>=2.3.1,<3.0.0)
Requires-Dist: requests (>=2.0.0,<3.0.0)
Requires-Dist: requests-toolbelt (>=1.0.0,<2.0.0)
Requires-Dist: segmentation-mask-overlay (>=0.3.4,<0.4.0)
Requires-Dist: snowflake-connector-python (>=3.10.0,<4.0.0) ; extra == "snowflake"
Requires-Dist: tenacity (>=8.2.3,<9.0.0)
Requires-Dist: tqdm (>=4.64.0,<5.0.0)
Requires-Dist: urllib3 (>=1.26.0,<2.0.0)
Project-URL: Homepage, https://landing.ai
Project-URL: documentation, https://landing-ai.github.io/landingai-python/landingai.html
Project-URL: repository, https://github.com/landing-ai/landingai-python
